{"date":1665257919749,"problems":[{"c":146,"n":"LRU Cache","u":"/problems/lru-cache","l":1,"f":134.5},{"c":362,"n":"Design Hit Counter","u":"/problems/design-hit-counter","l":1,"f":132.133},{"c":798,"n":"Smallest Rotation with Highest Score","u":"/problems/smallest-rotation-with-highest-score","l":0,"f":126.609},{"c":772,"n":"Basic Calculator III","u":"/problems/basic-calculator-iii","l":0,"f":118.758},{"c":284,"n":"Peeking Iterator","u":"/problems/peeking-iterator","l":1,"f":113.82},{"c":428,"n":"Serialize and Deserialize N-ary Tree","u":"/problems/serialize-and-deserialize-n-ary-tree","l":0,"f":105.961},{"c":443,"n":"String Compression","u":"/problems/string-compression","l":1,"f":102.422},{"c":895,"n":"Maximum Frequency Stack","u":"/problems/maximum-frequency-stack","l":0,"f":94.5703},{"c":400,"n":"Nth Digit","u":"/problems/nth-digit","l":1,"f":94.1484},{"c":1061,"n":"Lexicographically Smallest Equivalent String","u":"/problems/lexicographically-smallest-equivalent-string","l":1,"f":90.7578},{"c":1175,"n":"Prime Arrangements","u":"/problems/prime-arrangements","l":2,"f":87.6406},{"c":149,"n":"Max Points on a Line","u":"/problems/max-points-on-a-line","l":0,"f":84.75},{"c":629,"n":"K Inverse Pairs Array","u":"/problems/k-inverse-pairs-array","l":0,"f":84.75},{"c":13,"n":"Roman to Integer","u":"/problems/roman-to-integer","l":2,"f":82.0078},{"c":1658,"n":"Minimum Operations to Reduce X to Zero","u":"/problems/minimum-operations-to-reduce-x-to-zero","l":1,"f":80.1562},{"c":1,"n":"Two Sum","u":"/problems/two-sum","l":2,"f":75.7969},{"c":4,"n":"Median of Two Sorted Arrays","u":"/problems/median-of-two-sorted-arrays","l":0,"f":67.9453},{"c":273,"n":"Integer to English Words","u":"/problems/integer-to-english-words","l":0,"f":67.8906},{"c":36,"n":"Valid Sudoku","u":"/problems/valid-sudoku","l":1,"f":66.8672},{"c":730,"n":"Count Different Palindromic Subsequences","u":"/problems/count-different-palindromic-subsequences","l":0,"f":66.1016},{"c":583,"n":"Delete Operation for Two Strings","u":"/problems/delete-operation-for-two-strings","l":1,"f":65.7812},{"c":1268,"n":"Search Suggestions System","u":"/problems/search-suggestions-system","l":1,"f":64.7812},{"c":31,"n":"Next Permutation","u":"/problems/next-permutation","l":1,"f":63.6953},{"c":140,"n":"Word Break II","u":"/problems/word-break-ii","l":0,"f":62.7266},{"c":56,"n":"Merge Intervals","u":"/problems/merge-intervals","l":1,"f":62.6172},{"c":2008,"n":"Maximum Earnings From Taxi","u":"/problems/maximum-earnings-from-taxi","l":1,"f":60.2734},{"c":1696,"n":"Jump Game VI","u":"/problems/jump-game-vi","l":1,"f":58.9844},{"c":200,"n":"Number of Islands","u":"/problems/number-of-islands","l":1,"f":57.9922},{"c":325,"n":"Maximum Size Subarray Sum Equals k","u":"/problems/maximum-size-subarray-sum-equals-k","l":1,"f":56.3047},{"c":916,"n":"Word Subsets","u":"/problems/word-subsets","l":1,"f":56.3047},{"c":987,"n":"Vertical Order Traversal of a Binary Tree","u":"/problems/vertical-order-traversal-of-a-binary-tree","l":0,"f":55.8047},{"c":48,"n":"Rotate Image","u":"/problems/rotate-image","l":1,"f":54.7031},{"c":1039,"n":"Minimum Score Triangulation of Polygon","u":"/problems/minimum-score-triangulation-of-polygon","l":1,"f":54.3438},{"c":380,"n":"Insert Delete GetRandom O(1)","u":"/problems/insert-delete-getrandom-o1","l":1,"f":54.1719},{"c":1402,"n":"Reducing Dishes","u":"/problems/reducing-dishes","l":0,"f":53.4141},{"c":759,"n":"Employee Free Time","u":"/problems/employee-free-time","l":0,"f":52.5234},{"c":996,"n":"Number of Squareful Arrays","u":"/problems/number-of-squareful-arrays","l":0,"f":52.3047},{"c":295,"n":"Find Median from Data Stream","u":"/problems/find-median-from-data-stream","l":0,"f":52.0547},{"c":348,"n":"Design Tic-Tac-Toe","u":"/problems/design-tic-tac-toe","l":1,"f":51.2344},{"c":1024,"n":"Video Stitching","u":"/problems/video-stitching","l":1,"f":49.5234},{"c":15,"n":"3Sum","u":"/problems/3sum","l":1,"f":49.0625},{"c":1671,"n":"Minimum Number of Removals to Make Mountain Array","u":"/problems/minimum-number-of-removals-to-make-mountain-array","l":0,"f":47.8281},{"c":14,"n":"Longest Common Prefix","u":"/problems/longest-common-prefix","l":2,"f":47.3516},{"c":642,"n":"Design Search Autocomplete System","u":"/problems/design-search-autocomplete-system","l":0,"f":45.5078},{"c":311,"n":"Sparse Matrix Multiplication","u":"/problems/sparse-matrix-multiplication","l":1,"f":44.7812},{"c":823,"n":"Binary Trees With Factors","u":"/problems/binary-trees-with-factors","l":1,"f":44.0859},{"c":2,"n":"Add Two Numbers","u":"/problems/add-two-numbers","l":1,"f":43.0625},{"c":233,"n":"Number of Digit One","u":"/problems/number-of-digit-one","l":0,"f":42.3203},{"c":274,"n":"H-Index","u":"/problems/h-index","l":1,"f":42.0469},{"c":53,"n":"Maximum Subarray","u":"/problems/maximum-subarray","l":1,"f":41.6172},{"c":341,"n":"Flatten Nested List Iterator","u":"/problems/flatten-nested-list-iterator","l":1,"f":41.4922},{"c":659,"n":"Split Array into Consecutive Subsequences","u":"/problems/split-array-into-consecutive-subsequences","l":1,"f":40.3125},{"c":188,"n":"Best Time to Buy and Sell Stock IV","u":"/problems/best-time-to-buy-and-sell-stock-iv","l":0,"f":38.5391},{"c":30,"n":"Substring with Concatenation of All Words","u":"/problems/substring-with-concatenation-of-all-words","l":0,"f":37.7656},{"c":1044,"n":"Longest Duplicate Substring","u":"/problems/longest-duplicate-substring","l":0,"f":37.6406},{"c":697,"n":"Degree of an Array","u":"/problems/degree-of-an-array","l":2,"f":37.1484},{"c":1431,"n":"Kids With the Greatest Number of Candies","u":"/problems/kids-with-the-greatest-number-of-candies","l":2,"f":37.1484},{"c":346,"n":"Moving Average from Data Stream","u":"/problems/moving-average-from-data-stream","l":2,"f":36.7266},{"c":1642,"n":"Furthest Building You Can Reach","u":"/problems/furthest-building-you-can-reach","l":1,"f":36.5156},{"c":958,"n":"Check Completeness of a Binary Tree","u":"/problems/check-completeness-of-a-binary-tree","l":1,"f":36.2109},{"c":42,"n":"Trapping Rain Water","u":"/problems/trapping-rain-water","l":0,"f":35.9453},{"c":148,"n":"Sort List","u":"/problems/sort-list","l":1,"f":35.8047},{"c":384,"n":"Shuffle an Array","u":"/problems/shuffle-an-array","l":1,"f":35.5078},{"c":220,"n":"Contains Duplicate III","u":"/problems/contains-duplicate-iii","l":0,"f":35.3125},{"c":779,"n":"K-th Symbol in Grammar","u":"/problems/k-th-symbol-in-grammar","l":1,"f":34.9297},{"c":1009,"n":"Complement of Base 10 Integer","u":"/problems/complement-of-base-10-integer","l":2,"f":34.7734},{"c":37,"n":"Sudoku Solver","u":"/problems/sudoku-solver","l":0,"f":34.5547},{"c":198,"n":"House Robber","u":"/problems/house-robber","l":1,"f":34.1406},{"c":59,"n":"Spiral Matrix II","u":"/problems/spiral-matrix-ii","l":1,"f":33.9453},{"c":22,"n":"Generate Parentheses","u":"/problems/generate-parentheses","l":1,"f":32.8516},{"c":23,"n":"Merge k Sorted Lists","u":"/problems/merge-k-sorted-lists","l":0,"f":32.25},{"c":2193,"n":"Minimum Number of Moves to Make Palindrome","u":"/problems/minimum-number-of-moves-to-make-palindrome","l":0,"f":32.1328},{"c":394,"n":"Decode String","u":"/problems/decode-string","l":1,"f":32.0156},{"c":259,"n":"3Sum Smaller","u":"/problems/3sum-smaller","l":1,"f":31.7734},{"c":1219,"n":"Path with Maximum Gold","u":"/problems/path-with-maximum-gold","l":1,"f":31.0859},{"c":1275,"n":"Find Winner on a Tic Tac Toe Game","u":"/problems/find-winner-on-a-tic-tac-toe-game","l":2,"f":31.0859},{"c":456,"n":"132 Pattern","u":"/problems/132-pattern","l":1,"f":30.8984},{"c":49,"n":"Group Anagrams","u":"/problems/group-anagrams","l":1,"f":30.8203},{"c":227,"n":"Basic Calculator II","u":"/problems/basic-calculator-ii","l":1,"f":30.75},{"c":54,"n":"Spiral Matrix","u":"/problems/spiral-matrix","l":1,"f":30.6953},{"c":347,"n":"Top K Frequent Elements","u":"/problems/top-k-frequent-elements","l":1,"f":30.6875},{"c":239,"n":"Sliding Window Maximum","u":"/problems/sliding-window-maximum","l":0,"f":30.5156},{"c":381,"n":"Insert Delete GetRandom O(1) - Duplicates allowed","u":"/problems/insert-delete-getrandom-o1-duplicates-allowed","l":0,"f":30.4297},{"c":345,"n":"Reverse Vowels of a String","u":"/problems/reverse-vowels-of-a-string","l":2,"f":30.2656},{"c":948,"n":"Bag of Tokens","u":"/problems/bag-of-tokens","l":1,"f":30.1094},{"c":128,"n":"Longest Consecutive Sequence","u":"/problems/longest-consecutive-sequence","l":1,"f":30.0859},{"c":684,"n":"Redundant Connection","u":"/problems/redundant-connection","l":1,"f":29.5625},{"c":890,"n":"Find and Replace Pattern","u":"/problems/find-and-replace-pattern","l":1,"f":29.4922},{"c":217,"n":"Contains Duplicate","u":"/problems/contains-duplicate","l":2,"f":29.3672},{"c":121,"n":"Best Time to Buy and Sell Stock","u":"/problems/best-time-to-buy-and-sell-stock","l":2,"f":29.25},{"c":229,"n":"Majority Element II","u":"/problems/majority-element-ii","l":1,"f":29.2031},{"c":1770,"n":"Maximum Score from Performing Multiplication Operations","u":"/problems/maximum-score-from-performing-multiplication-operations","l":0,"f":29.1875},{"c":74,"n":"Search a 2D Matrix","u":"/problems/search-a-2d-matrix","l":1,"f":29.0859},{"c":1282,"n":"Group the People Given the Group Size They Belong To","u":"/problems/group-the-people-given-the-group-size-they-belong-to","l":1,"f":28.3281},{"c":869,"n":"Reordered Power of 2","u":"/problems/reordered-power-of-2","l":1,"f":28.0469},{"c":179,"n":"Largest Number","u":"/problems/largest-number","l":1,"f":27.7109},{"c":508,"n":"Most Frequent Subtree Sum","u":"/problems/most-frequent-subtree-sum","l":1,"f":27.25},{"c":990,"n":"Satisfiability of Equality Equations","u":"/problems/satisfiability-of-equality-equations","l":1,"f":27.25},{"c":468,"n":"Validate IP Address","u":"/problems/validate-ip-address","l":1,"f":26.2578},{"c":3,"n":"Longest Substring Without Repeating Characters","u":"/problems/longest-substring-without-repeating-characters","l":1,"f":25.8828},{"c":704,"n":"Binary Search","u":"/problems/binary-search","l":2,"f":24.9219},{"c":1710,"n":"Maximum Units on a Truck","u":"/problems/maximum-units-on-a-truck","l":2,"f":24.6562},{"c":1394,"n":"Find Lucky Integer in an Array","u":"/problems/find-lucky-integer-in-an-array","l":2,"f":23.2812},{"c":224,"n":"Basic Calculator","u":"/problems/basic-calculator","l":0,"f":23.2422},{"c":25,"n":"Reverse Nodes in k-Group","u":"/problems/reverse-nodes-in-k-group","l":0,"f":22.9453},{"c":746,"n":"Min Cost Climbing Stairs","u":"/problems/min-cost-climbing-stairs","l":2,"f":22.6172},{"c":301,"n":"Remove Invalid Parentheses","u":"/problems/remove-invalid-parentheses","l":0,"f":22.5547},{"c":1146,"n":"Snapshot Array","u":"/problems/snapshot-array","l":1,"f":22.3828},{"c":120,"n":"Triangle","u":"/problems/triangle","l":1,"f":22},{"c":523,"n":"Continuous Subarray Sum","u":"/problems/continuous-subarray-sum","l":1,"f":21.7656},{"c":2235,"n":"Add Two Integers","u":"/problems/add-two-integers","l":2,"f":21.7266},{"c":871,"n":"Minimum Number of Refueling Stops","u":"/problems/minimum-number-of-refueling-stops","l":0,"f":21.7109},{"c":658,"n":"Find K Closest Elements","u":"/problems/find-k-closest-elements","l":1,"f":21.3828},{"c":285,"n":"Inorder Successor in BST","u":"/problems/inorder-successor-in-bst","l":1,"f":21.0703},{"c":1547,"n":"Minimum Cost to Cut a Stick","u":"/problems/minimum-cost-to-cut-a-stick","l":0,"f":20.7734},{"c":328,"n":"Odd Even Linked List","u":"/problems/odd-even-linked-list","l":1,"f":20.5156},{"c":460,"n":"LFU Cache","u":"/problems/lfu-cache","l":0,"f":20.4766},{"c":904,"n":"Fruit Into Baskets","u":"/problems/fruit-into-baskets","l":1,"f":20.4609},{"c":75,"n":"Sort Colors","u":"/problems/sort-colors","l":1,"f":20.3906},{"c":992,"n":"Subarrays with K Different Integers","u":"/problems/subarrays-with-k-different-integers","l":0,"f":20.0469},{"c":210,"n":"Course Schedule II","u":"/problems/course-schedule-ii","l":1,"f":19.8438},{"c":383,"n":"Ransom Note","u":"/problems/ransom-note","l":2,"f":19.5547},{"c":7,"n":"Reverse Integer","u":"/problems/reverse-integer","l":1,"f":19.4375},{"c":647,"n":"Palindromic Substrings","u":"/problems/palindromic-substrings","l":1,"f":19.3125},{"c":706,"n":"Design HashMap","u":"/problems/design-hashmap","l":2,"f":19.1328},{"c":189,"n":"Rotate Array","u":"/problems/rotate-array","l":1,"f":19.0312},{"c":174,"n":"Dungeon Game","u":"/problems/dungeon-game","l":0,"f":18.5078},{"c":238,"n":"Product of Array Except Self","u":"/problems/product-of-array-except-self","l":1,"f":18.3125},{"c":17,"n":"Letter Combinations of a Phone Number","u":"/problems/letter-combinations-of-a-phone-number","l":1,"f":18.2891},{"c":19,"n":"Remove Nth Node From End of List","u":"/problems/remove-nth-node-from-end-of-list","l":1,"f":17.9062},{"c":1209,"n":"Remove All Adjacent Duplicates in String II","u":"/problems/remove-all-adjacent-duplicates-in-string-ii","l":1,"f":17.8281},{"c":1094,"n":"Car Pooling","u":"/problems/car-pooling","l":1,"f":17.2891},{"c":62,"n":"Unique Paths","u":"/problems/unique-paths","l":1,"f":17.2812},{"c":50,"n":"Pow(x, n)","u":"/problems/powx-n","l":1,"f":17.2734},{"c":785,"n":"Is Graph Bipartite?","u":"/problems/is-graph-bipartite","l":1,"f":17.2578},{"c":1143,"n":"Longest Common Subsequence","u":"/problems/longest-common-subsequence","l":1,"f":17.0391},{"c":322,"n":"Coin Change","u":"/problems/coin-change","l":1,"f":16.9922},{"c":540,"n":"Single Element in a Sorted Array","u":"/problems/single-element-in-a-sorted-array","l":1,"f":16.5547},{"c":21,"n":"Merge Two Sorted Lists","u":"/problems/merge-two-sorted-lists","l":2,"f":16.4531},{"c":93,"n":"Restore IP Addresses","u":"/problems/restore-ip-addresses","l":1,"f":16.3203},{"c":621,"n":"Task Scheduler","u":"/problems/task-scheduler","l":1,"f":15.6797},{"c":312,"n":"Burst Balloons","u":"/problems/burst-balloons","l":0,"f":15.4453},{"c":349,"n":"Intersection of Two Arrays","u":"/problems/intersection-of-two-arrays","l":2,"f":15.4453},{"c":34,"n":"Find First and Last Position of Element in Sorted Array","u":"/problems/find-first-and-last-position-of-element-in-sorted-array","l":1,"f":15.4375},{"c":852,"n":"Peak Index in a Mountain Array","u":"/problems/peak-index-in-a-mountain-array","l":1,"f":15.3281},{"c":5,"n":"Longest Palindromic Substring","u":"/problems/longest-palindromic-substring","l":1,"f":15.25},{"c":316,"n":"Remove Duplicate Letters","u":"/problems/remove-duplicate-letters","l":1,"f":15.125},{"c":218,"n":"The Skyline Problem","u":"/problems/the-skyline-problem","l":0,"f":14.9688},{"c":95,"n":"Unique Binary Search Trees II","u":"/problems/unique-binary-search-trees-ii","l":1,"f":14.8906},{"c":206,"n":"Reverse Linked List","u":"/problems/reverse-linked-list","l":2,"f":14.8516},{"c":79,"n":"Word Search","u":"/problems/word-search","l":1,"f":14.7812},{"c":183,"n":"Customers Who Never Order","u":"/problems/customers-who-never-order","l":2,"f":14.5078},{"c":503,"n":"Next Greater Element II","u":"/problems/next-greater-element-ii","l":1,"f":14.3984},{"c":416,"n":"Partition Equal Subset Sum","u":"/problems/partition-equal-subset-sum","l":1,"f":14.0781},{"c":541,"n":"Reverse String II","u":"/problems/reverse-string-ii","l":2,"f":13.9609},{"c":714,"n":"Best Time to Buy and Sell Stock with Transaction Fee","u":"/problems/best-time-to-buy-and-sell-stock-with-transaction-fee","l":1,"f":13.8906},{"c":26,"n":"Remove Duplicates from Sorted Array","u":"/problems/remove-duplicates-from-sorted-array","l":2,"f":13.8906},{"c":44,"n":"Wildcard Matching","u":"/problems/wildcard-matching","l":0,"f":13.7578},{"c":212,"n":"Word Search II","u":"/problems/word-search-ii","l":0,"f":13.3359},{"c":315,"n":"Count of Smaller Numbers After Self","u":"/problems/count-of-smaller-numbers-after-self","l":0,"f":13.3203},{"c":234,"n":"Palindrome Linked List","u":"/problems/palindrome-linked-list","l":2,"f":13.1719},{"c":410,"n":"Split Array Largest Sum","u":"/problems/split-array-largest-sum","l":0,"f":13.0781},{"c":415,"n":"Add Strings","u":"/problems/add-strings","l":2,"f":13.0703},{"c":207,"n":"Course Schedule","u":"/problems/course-schedule","l":1,"f":12.9297},{"c":367,"n":"Valid Perfect Square","u":"/problems/valid-perfect-square","l":2,"f":12.8672},{"c":134,"n":"Gas Station","u":"/problems/gas-station","l":1,"f":12.6875},{"c":455,"n":"Assign Cookies","u":"/problems/assign-cookies","l":2,"f":12.5703},{"c":86,"n":"Partition List","u":"/problems/partition-list","l":1,"f":12.5156},{"c":11,"n":"Container With Most Water","u":"/problems/container-with-most-water","l":1,"f":12.2578},{"c":721,"n":"Accounts Merge","u":"/problems/accounts-merge","l":1,"f":12.1484},{"c":912,"n":"Sort an Array","u":"/problems/sort-an-array","l":1,"f":12.0781},{"c":76,"n":"Minimum Window Substring","u":"/problems/minimum-window-substring","l":0,"f":12.0312},{"c":242,"n":"Valid Anagram","u":"/problems/valid-anagram","l":2,"f":11.9766},{"c":2089,"n":"Find Target Indices After Sorting Array","u":"/problems/find-target-indices-after-sorting-array","l":2,"f":11.7031},{"c":493,"n":"Reverse Pairs","u":"/problems/reverse-pairs","l":0,"f":11.5234},{"c":532,"n":"K-diff Pairs in an Array","u":"/problems/k-diff-pairs-in-an-array","l":1,"f":11.4766},{"c":1048,"n":"Longest String Chain","u":"/problems/longest-string-chain","l":1,"f":11.4297},{"c":832,"n":"Flipping an Image","u":"/problems/flipping-an-image","l":2,"f":11.25},{"c":997,"n":"Find the Town Judge","u":"/problems/find-the-town-judge","l":2,"f":11.125},{"c":141,"n":"Linked List Cycle","u":"/problems/linked-list-cycle","l":2,"f":10.75},{"c":560,"n":"Subarray Sum Equals K","u":"/problems/subarray-sum-equals-k","l":1,"f":10.6797},{"c":137,"n":"Single Number II","u":"/problems/single-number-ii","l":1,"f":10.5156},{"c":796,"n":"Rotate String","u":"/problems/rotate-string","l":2,"f":10.5156},{"c":231,"n":"Power of Two","u":"/problems/power-of-two","l":2,"f":10.4688},{"c":73,"n":"Set Matrix Zeroes","u":"/problems/set-matrix-zeroes","l":1,"f":10.3828},{"c":160,"n":"Intersection of Two Linked Lists","u":"/problems/intersection-of-two-linked-lists","l":2,"f":10.3594},{"c":67,"n":"Add Binary","u":"/problems/add-binary","l":2,"f":10.2422},{"c":253,"n":"Meeting Rooms II","u":"/problems/meeting-rooms-ii","l":1,"f":10.0859},{"c":97,"n":"Interleaving String","u":"/problems/interleaving-string","l":1,"f":10.0078},{"c":180,"n":"Consecutive Numbers","u":"/problems/consecutive-numbers","l":1,"f":9.875},{"c":151,"n":"Reverse Words in a String","u":"/problems/reverse-words-in-a-string","l":1,"f":9.84375},{"c":115,"n":"Distinct Subsequences","u":"/problems/distinct-subsequences","l":0,"f":9.80469},{"c":139,"n":"Word Break","u":"/problems/word-break","l":1,"f":9.64844},{"c":938,"n":"Range Sum of BST","u":"/problems/range-sum-of-bst","l":2,"f":9.57812},{"c":168,"n":"Excel Sheet Column Title","u":"/problems/excel-sheet-column-title","l":2,"f":9.54688},{"c":99,"n":"Recover Binary Search Tree","u":"/problems/recover-binary-search-tree","l":1,"f":9.33594},{"c":215,"n":"Kth Largest Element in an Array","u":"/problems/kth-largest-element-in-an-array","l":1,"f":9.3125},{"c":344,"n":"Reverse String","u":"/problems/reverse-string","l":2,"f":9.27344},{"c":209,"n":"Minimum Size Subarray Sum","u":"/problems/minimum-size-subarray-sum","l":1,"f":9.20312},{"c":222,"n":"Count Complete Tree Nodes","u":"/problems/count-complete-tree-nodes","l":1,"f":8.98438},{"c":35,"n":"Search Insert Position","u":"/problems/search-insert-position","l":2,"f":8.73438},{"c":450,"n":"Delete Node in a BST","u":"/problems/delete-node-in-a-bst","l":1,"f":8.71875},{"c":202,"n":"Happy Number","u":"/problems/happy-number","l":2,"f":8.69531},{"c":103,"n":"Binary Tree Zigzag Level Order Traversal","u":"/problems/binary-tree-zigzag-level-order-traversal","l":1,"f":8.64062},{"c":18,"n":"4Sum","u":"/problems/4sum","l":1,"f":8.57812},{"c":105,"n":"Construct Binary Tree from Preorder and Inorder Traversal","u":"/problems/construct-binary-tree-from-preorder-and-inorder-traversal","l":1,"f":8.5625},{"c":279,"n":"Perfect Squares","u":"/problems/perfect-squares","l":1,"f":8.53906},{"c":136,"n":"Single Number","u":"/problems/single-number","l":2,"f":8.46094},{"c":55,"n":"Jump Game","u":"/problems/jump-game","l":1,"f":8.29688},{"c":221,"n":"Maximal Square","u":"/problems/maximal-square","l":1,"f":8.27344},{"c":287,"n":"Find the Duplicate Number","u":"/problems/find-the-duplicate-number","l":1,"f":8.03906},{"c":98,"n":"Validate Binary Search Tree","u":"/problems/validate-binary-search-tree","l":1,"f":8.03125},{"c":96,"n":"Unique Binary Search Trees","u":"/problems/unique-binary-search-trees","l":1,"f":7.92969},{"c":735,"n":"Asteroid Collision","u":"/problems/asteroid-collision","l":1,"f":7.89062},{"c":57,"n":"Insert Interval","u":"/problems/insert-interval","l":1,"f":7.875},{"c":211,"n":"Design Add and Search Words Data Structure","u":"/problems/design-add-and-search-words-data-structure","l":1,"f":7.74219},{"c":994,"n":"Rotting Oranges","u":"/problems/rotting-oranges","l":1,"f":7.60938},{"c":6,"n":"Zigzag Conversion","u":"/problems/zigzag-conversion","l":1,"f":7.57031},{"c":8,"n":"String to Integer (atoi)","u":"/problems/string-to-integer-atoi","l":1,"f":7.54688},{"c":1929,"n":"Concatenation of Array","u":"/problems/concatenation-of-array","l":2,"f":7.54688},{"c":167,"n":"Two Sum II - Input Array Is Sorted","u":"/problems/two-sum-ii-input-array-is-sorted","l":1,"f":7.32812},{"c":125,"n":"Valid Palindrome","u":"/problems/valid-palindrome","l":2,"f":7.32031},{"c":33,"n":"Search in Rotated Sorted Array","u":"/problems/search-in-rotated-sorted-array","l":1,"f":7.28125},{"c":38,"n":"Count and Say","u":"/problems/count-and-say","l":1,"f":7.25781},{"c":41,"n":"First Missing Positive","u":"/problems/first-missing-positive","l":0,"f":7.15625},{"c":84,"n":"Largest Rectangle in Histogram","u":"/problems/largest-rectangle-in-histogram","l":0,"f":7.07031},{"c":124,"n":"Binary Tree Maximum Path Sum","u":"/problems/binary-tree-maximum-path-sum","l":0,"f":7.07031},{"c":586,"n":"Customer Placing the Largest Number of Orders","u":"/problems/customer-placing-the-largest-number-of-orders","l":2,"f":6.79688},{"c":1207,"n":"Unique Number of Occurrences","u":"/problems/unique-number-of-occurrences","l":2,"f":6.75},{"c":509,"n":"Fibonacci Number","u":"/problems/fibonacci-number","l":2,"f":6.59375},{"c":371,"n":"Sum of Two Integers","u":"/problems/sum-of-two-integers","l":1,"f":6.46875},{"c":692,"n":"Top K Frequent Words","u":"/problems/top-k-frequent-words","l":1,"f":6.45312},{"c":875,"n":"Koko Eating Bananas","u":"/problems/koko-eating-bananas","l":1,"f":6.1875},{"c":122,"n":"Best Time to Buy and Sell Stock II","u":"/problems/best-time-to-buy-and-sell-stock-ii","l":1,"f":6.15625},{"c":51,"n":"N-Queens","u":"/problems/n-queens","l":0,"f":6.10156},{"c":297,"n":"Serialize and Deserialize Binary Tree","u":"/problems/serialize-and-deserialize-binary-tree","l":0,"f":5.96094},{"c":1470,"n":"Shuffle the Array","u":"/problems/shuffle-the-array","l":2,"f":5.89062},{"c":278,"n":"First Bad Version","u":"/problems/first-bad-version","l":2,"f":5.84375},{"c":155,"n":"Min Stack","u":"/problems/min-stack","l":1,"f":5.75781},{"c":442,"n":"Find All Duplicates in an Array","u":"/problems/find-all-duplicates-in-an-array","l":1,"f":5.64844},{"c":387,"n":"First Unique Character in a String","u":"/problems/first-unique-character-in-a-string","l":2,"f":5.64062},{"c":2236,"n":"Root Equals Sum of Children","u":"/problems/root-equals-sum-of-children","l":2,"f":5.64062},{"c":417,"n":"Pacific Atlantic Water Flow","u":"/problems/pacific-atlantic-water-flow","l":1,"f":5.625},{"c":127,"n":"Word Ladder","u":"/problems/word-ladder","l":0,"f":5.5625},{"c":1137,"n":"N-th Tribonacci Number","u":"/problems/n-th-tribonacci-number","l":2,"f":5.53125},{"c":72,"n":"Edit Distance","u":"/problems/edit-distance","l":0,"f":5.50781},{"c":20,"n":"Valid Parentheses","u":"/problems/valid-parentheses","l":2,"f":5.46875},{"c":66,"n":"Plus One","u":"/problems/plus-one","l":2,"f":5.39844},{"c":374,"n":"Guess Number Higher or Lower","u":"/problems/guess-number-higher-or-lower","l":2,"f":5.39844},{"c":28,"n":"Find the Index of the First Occurrence in a String","u":"/problems/find-the-index-of-the-first-occurrence-in-a-string","l":1,"f":5.21875},{"c":300,"n":"Longest Increasing Subsequence","u":"/problems/longest-increasing-subsequence","l":1,"f":5.16406},{"c":153,"n":"Find Minimum in Rotated Sorted Array","u":"/problems/find-minimum-in-rotated-sorted-array","l":1,"f":5.09375},{"c":104,"n":"Maximum Depth of Binary Tree","u":"/problems/maximum-depth-of-binary-tree","l":2,"f":5.08594},{"c":88,"n":"Merge Sorted Array","u":"/problems/merge-sorted-array","l":2,"f":5.0625},{"c":240,"n":"Search a 2D Matrix II","u":"/problems/search-a-2d-matrix-ii","l":1,"f":5.04688},{"c":680,"n":"Valid Palindrome II","u":"/problems/valid-palindrome-ii","l":2,"f":5.02344},{"c":114,"n":"Flatten Binary Tree to Linked List","u":"/problems/flatten-binary-tree-to-linked-list","l":1,"f":4.96094},{"c":101,"n":"Symmetric Tree","u":"/problems/symmetric-tree","l":2,"f":4.9375},{"c":138,"n":"Copy List with Random Pointer","u":"/problems/copy-list-with-random-pointer","l":1,"f":4.82031},{"c":595,"n":"Big Countries","u":"/problems/big-countries","l":2,"f":4.78125},{"c":977,"n":"Squares of a Sorted Array","u":"/problems/squares-of-a-sorted-array","l":2,"f":4.73438},{"c":876,"n":"Middle of the Linked List","u":"/problems/middle-of-the-linked-list","l":2,"f":4.6875},{"c":32,"n":"Longest Valid Parentheses","u":"/problems/longest-valid-parentheses","l":0,"f":4.64062},{"c":557,"n":"Reverse Words in a String III","u":"/problems/reverse-words-in-a-string-iii","l":2,"f":4.5625},{"c":547,"n":"Number of Provinces","u":"/problems/number-of-provinces","l":1,"f":4.54688},{"c":118,"n":"Pascal's Triangle","u":"/problems/pascals-triangle","l":2,"f":4.5},{"c":448,"n":"Find All Numbers Disappeared in an Array","u":"/problems/find-all-numbers-disappeared-in-an-array","l":2,"f":4.42969},{"c":695,"n":"Max Area of Island","u":"/problems/max-area-of-island","l":1,"f":4.3125},{"c":143,"n":"Reorder List","u":"/problems/reorder-list","l":1,"f":4.21875},{"c":10,"n":"Regular Expression Matching","u":"/problems/regular-expression-matching","l":0,"f":4.0625},{"c":237,"n":"Delete Node in a Linked List","u":"/problems/delete-node-in-a-linked-list","l":1,"f":3.99219},{"c":100,"n":"Same Tree","u":"/problems/same-tree","l":2,"f":3.94531},{"c":108,"n":"Convert Sorted Array to Binary Search Tree","u":"/problems/convert-sorted-array-to-binary-search-tree","l":2,"f":3.89062},{"c":133,"n":"Clone Graph","u":"/problems/clone-graph","l":1,"f":3.82812},{"c":572,"n":"Subtree of Another Tree","u":"/problems/subtree-of-another-tree","l":2,"f":3.79688},{"c":69,"n":"Sqrt(x)","u":"/problems/sqrtx","l":2,"f":3.76562},{"c":169,"n":"Majority Element","u":"/problems/majority-element","l":2,"f":3.69531},{"c":90,"n":"Subsets II","u":"/problems/subsets-ii","l":1,"f":3.61719},{"c":29,"n":"Divide Two Integers","u":"/problems/divide-two-integers","l":1,"f":3.5},{"c":24,"n":"Swap Nodes in Pairs","u":"/problems/swap-nodes-in-pairs","l":1,"f":3.39844},{"c":424,"n":"Longest Repeating Character Replacement","u":"/problems/longest-repeating-character-replacement","l":1,"f":3.23438},{"c":567,"n":"Permutation in String","u":"/problems/permutation-in-string","l":1,"f":3.09375},{"c":162,"n":"Find Peak Element","u":"/problems/find-peak-element","l":1,"f":3.0625},{"c":236,"n":"Lowest Common Ancestor of a Binary Tree","u":"/problems/lowest-common-ancestor-of-a-binary-tree","l":1,"f":3.0625},{"c":203,"n":"Remove Linked List Elements","u":"/problems/remove-linked-list-elements","l":2,"f":3.04688},{"c":144,"n":"Binary Tree Preorder Traversal","u":"/problems/binary-tree-preorder-traversal","l":2,"f":2.57812},{"c":16,"n":"3Sum Closest","u":"/problems/3sum-closest","l":1,"f":2.57031},{"c":733,"n":"Flood Fill","u":"/problems/flood-fill","l":2,"f":2.48438},{"c":235,"n":"Lowest Common Ancestor of a Binary Search Tree","u":"/problems/lowest-common-ancestor-of-a-binary-search-tree","l":1,"f":2.42188},{"c":83,"n":"Remove Duplicates from Sorted List","u":"/problems/remove-duplicates-from-sorted-list","l":2,"f":2.32031},{"c":78,"n":"Subsets","u":"/problems/subsets","l":1,"f":2.3125},{"c":70,"n":"Climbing Stairs","u":"/problems/climbing-stairs","l":2,"f":2.14844},{"c":39,"n":"Combination Sum","u":"/problems/combination-sum","l":1,"f":2.10156},{"c":1480,"n":"Running Sum of 1d Array","u":"/problems/running-sum-of-1d-array","l":2,"f":2.02344},{"c":46,"n":"Permutations","u":"/problems/permutations","l":1,"f":1.96094},{"c":412,"n":"Fizz Buzz","u":"/problems/fizz-buzz","l":2,"f":1.69531},{"c":226,"n":"Invert Binary Tree","u":"/problems/invert-binary-tree","l":2,"f":1.625},{"c":9,"n":"Palindrome Number","u":"/problems/palindrome-number","l":2,"f":1.55469},{"c":283,"n":"Move Zeroes","u":"/problems/move-zeroes","l":2,"f":1.33594},{"c":27,"n":"Remove Element","u":"/problems/remove-element","l":2,"f":1.32031},{"c":724,"n":"Find Pivot Index","u":"/problems/find-pivot-index","l":2,"f":1.3125}]}